{
  "query": "깊은잠베개",
  "total_ads": 4,
  "unique_ads": 1,
  "crawl_date": "2026-02-11T17:30:20.586749",
  "elapsed_seconds": 18.758459,
  "ads": [
    {
      "advertiser": "jion.byon",
      "ad_id": "1751264899611888",
      "ad_library_url": "https://www.facebook.com/ads/library/?id=1751264899611888",
      "thumbnail_url": "https://scontent-icn2-1.xx.fbcdn.net/v/t39.35426-6/622859943_924466709916569_3355739319051837262_n.jpg?stp=dst-jpg_s60x60_tt6&_nc_cat=106&ccb=1-7&_nc_sid=c53f8f&_nc_ohc=fywGHGwogBMQ7kNvwFPyuw7&_nc_oc=AdlCEwJhqjLga-w1RpOSs61z-qB87EOc_Prf1kuEe1AJW8HoAeYEdokqT_8iomxG1so&_nc_zt=14&_nc_ht=scontent-icn2-1.xx&_nc_gid=wrtl3xBKNgDSwVvZ6XnDzA&oh=00_AfvohgF57fSC7YMHe7b2KQd5SunQPmQEOvkanDFLNoWyDQ&oe=6991F8F7",
      "video_url": "",
      "media_type": "image",
      "ad_text": "[이벤트 있어요] 자고 일어나면 늘 승모근, 어깨 통증 때문에 \n하루가 상쾌하지 않았는데 \n이게 바로 베개의 지지력 때문일 수 있다니?! \n \n시중에 좋다는 경추 베개 다 사용해보고 가장 만족스러웠던 아이유베개! \n이브자리 수면환경 연구소에서 10년 연구 결과 끝에 개발된 꿀잠베개에요 \n \n뒤척임에 최적화된 4분할 구조라 \n정면/측면 어느 자세로도 편안한 숙면이 가능하다고..!! \n진짜 옆으로 자도 목, 어깨가 아프지 않더라구요 :) \n \n게다가 마감 박음질이 예술인데 \n커버분리 없이 통으로 세탁이 가능하고 \n세탁 후에도 닳지 않는 탄탄한 내구성까지 맘에 쏙 들어요! \n \n요즘 너무 잘 쓰고 있는 아이유베개와 좋은 인연이 닿아 \n댓글 달아주시는 온둥이들 중 한 분을 뽑아서 \n5,000원에 구매하실 수 있는 쿠폰을 선물로 드릴게요 ! \n \n[EVENT]\n- 당첨 경품: 슬립앤슬립 깊은잠베개(S 사이즈) 5,000원 구매쿠폰\n(정품을 5,000원에 구매할 수 있는 쿠폰이며, 배송비는 무료로 제공됩니다.)\n- 이벤트 방식: 아이유베개에 대한 기대평 댓글로 작성\n- 당첨자 발표: 11월 6일\n- 당첨자: 댓글 작성자 중 1인 추첨“ \n \n#슬립앤슬립#깊은잠베개#슬립앤슬립베개#아이유베개#기능성베개#경추베개",
      "impression_text": "",
      "start_date_raw": "2026. 1. 29.에 게재 시작함",
      "start_date": "2026-01-29",
      "days_live": 13,
      "status": "활성",
      "platforms": [],
      "query": "깊은잠베개",
      "platform": "meta_ad_library",
      "rank": 1,
      "crawl_date": "2026-02-11T17:30:07.609323"
    }
  ]
}